{
  "hash": "2f285e89",
  "browserHash": "81c4b564",
  "optimized": {
    "react": {
      "src": "../../node_modules/react/index.js",
      "file": "react.js",
      "fileHash": "a28db484",
      "needsInterop": true
    },
    "react-dom/client": {
      "src": "../../node_modules/react-dom/client.js",
      "file": "react-dom_client.js",
      "fileHash": "d96174ec",
      "needsInterop": true
    },
    "react-router-dom": {
      "src": "../../node_modules/react-router-dom/dist/index.js",
      "file": "react-router-dom.js",
      "fileHash": "1261e503",
      "needsInterop": false
    }
  },
  "chunks": {
    "chunk-QSQYAWSL": {
      "file": "chunk-QSQYAWSL.js"
    }
  }
}